pytvc/__init__.py
pytvc/control.py
pytvc/core.py
pytvc/data.py
pytvc/physics.py
pytvc/test_unittest.py
pytvc-0.1.3.data/scripts/control.py
pytvc-0.1.3.data/scripts/core.py
pytvc-0.1.3.data/scripts/data.py
pytvc-0.1.3.data/scripts/physics.py
pytvc-0.1.3.dist-info/METADATA
pytvc-0.1.3.dist-info/WHEEL
pytvc-0.1.3.dist-info/top_level.txt
pytvc-0.1.3.dist-info/RECORD
