Metadata-Version: 2.1
Name: pytvc
Version: 0.1.3
Summary: Python simulation tool for TVC
Author: ZegesMenden
License: UNKNOWN
Platform: UNKNOWN
